{
  "version": "2.3.5",
  "flags": {},
  "shapes": [
    {
      "label": "t_head",
      "points": [
        [
          302.77777777777777,
          193.05555555555554
        ],
        [
          315.4761904761905,
          193.05555555555554
        ],
        [
          315.4761904761905,
          206.94444444444443
        ],
        [
          302.77777777777777,
          206.94444444444443
        ]
      ],
      "group_id": null,
      "description": "",
      "difficult": false,
      "shape_type": "rectangle",
      "flags": {},
      "attributes": {}
    },
    {
      "label": "t_body",
      "points": [
        [
          296.8253968253968,
          193.45238095238093
        ],
        [
          332.53968253968253,
          193.45238095238093
        ],
        [
          332.53968253968253,
          237.10317460317458
        ],
        [
          296.8253968253968,
          237.10317460317458
        ]
      ],
      "group_id": null,
      "description": "",
      "difficult": false,
      "shape_type": "rectangle",
      "flags": {},
      "attributes": {}
    }
  ],
  "imagePath": "1716621268.png",
  "imageData": null,
  "imageHeight": 500,
  "imageWidth": 500
}